image_data.py
server.py
wx_article_mcp-0.2.0.dist-info/METADATA
wx_article_mcp-0.2.0.dist-info/WHEEL
wx_article_mcp-0.2.0.dist-info/entry_points.txt
wx_article_mcp-0.2.0.dist-info/top_level.txt
wx_article_mcp-0.2.0.dist-info/RECORD
