Metadata-Version: 2.4
Name: wx-article-mcp
Version: 0.2.0
Summary: 微信公众号MCP服务器，提供微信公众号文章发布功能
Author-email: Jewei <jiweifong@qq.com>
License: MIT
Project-URL: Homepage, https://github.com/jeweis/wx-article-mcp
Project-URL: Bug Tracker, https://github.com/jeweis/wx-article-mcp/issues
Classifier: Programming Language :: Python :: 3
Classifier: Operating System :: OS Independent
Requires-Python: >=3.10
Requires-Dist: fastmcp>=0.1.0
Requires-Dist: requests>=2.31.0
Requires-Dist: python-dotenv>=1.0.0
Requires-Dist: pydantic>=2.5.0
Requires-Dist: uvicorn>=0.24.0
Requires-Dist: beautifulsoup4>=4.12.0
Requires-Dist: markdown>=3.5.0
Requires-Dist: pygments>=2.16.0
Requires-Dist: pymdown-extensions>=10.0.0
Requires-Dist: mermaid-cli>=0.1.0
